[
    {
        "": "0",
        "Adj Year": "1",
        "Type": "Contributions",
        "Actual Accum": "284986",
        "Actual Flows": "284986",
        "Cashflow Forecast": "284986.0",
        "Accum CF Forecast": "284986.0",
        "Actual Accum Flows %": "0.284986",
        "Accum FC Flows %": "0.284986"
    },
    {
        "": "1",
        "Adj Year": "5",
        "Type": "Contributions",
        "Actual Accum": "525810",
        "Actual Flows": "240824",
        "Cashflow Forecast": "39674.65499999997",
        "Accum CF Forecast": "324660.65499999997",
        "Actual Accum Flows %": "0.52581",
        "Accum FC Flows %": "0.32466065499999996"
    },
    {
        "": "2",
        "Adj Year": "6",
        "Type": "Contributions",
        "Actual Accum": "916902",
        "Actual Flows": "391092",
        "Cashflow Forecast": "0.0",
        "Accum CF Forecast": "324660.65499999997",
        "Actual Accum Flows %": "0.916902",
        "Accum FC Flows %": "0.32466065499999996"
    },
    {
        "": "3",
        "Adj Year": "6",
        "Type": "Contributions",
        "Actual Accum": "1072191",
        "Actual Flows": "155289",
        "Cashflow Forecast": "0.0",
        "Accum CF Forecast": "324660.65499999997",
        "Actual Accum Flows %": "1.072191",
        "Accum FC Flows %": "0.32466065499999996"
    },
    {
        "": "4",
        "Adj Year": "6",
        "Type": "Contributions",
        "Actual Accum": "1131535",
        "Actual Flows": "59344",
        "Cashflow Forecast": "0.0",
        "Accum CF Forecast": "324660.65499999997",
        "Actual Accum Flows %": "1.131535",
        "Accum FC Flows %": "0.32466065499999996"
    },
    {
        "": "5",
        "Adj Year": "6",
        "Type": "Contributions",
        "Actual Accum": "1135315",
        "Actual Flows": "3780",
        "Cashflow Forecast": "0.0",
        "Accum CF Forecast": "324660.65499999997",
        "Actual Accum Flows %": "1.135315",
        "Accum FC Flows %": "0.32466065499999996"
    }
]